tellweather/cli.py
tellweather/utils.py
tellweather-1.1.dist-info/LICENSE
tellweather-1.1.dist-info/METADATA
tellweather-1.1.dist-info/WHEEL
tellweather-1.1.dist-info/entry_points.txt
tellweather-1.1.dist-info/top_level.txt
tellweather-1.1.dist-info/RECORD
