Metadata-Version: 2.1
Name: tellweather
Version: 1.1
Summary: A Python package to get weather reports for any location.
Home-page: https://github.com/mantej1995/Upwork/tree/main/upwork/tellweather
Author: Mantej Singh
Author-email: mantejsgill@gmail.com
License: MIT
Platform: UNKNOWN
Classifier: License :: OSI Approved :: MIT License
Classifier: Programming Language :: Python :: 3
Classifier: Programming Language :: Python :: 3.7
Requires-Dist: requests
